scikit_rest/__init__.py
scikit_rest/resource.py
scikit_rest/types.py
scikit_rest/validator.py
scikit_rest-0.1.1.dist-info/LICENSE
scikit_rest-0.1.1.dist-info/WHEEL
scikit_rest-0.1.1.dist-info/METADATA
scikit_rest-0.1.1.dist-info/RECORD
